{"gameId":"0022401193","season":"2024-25","homeWon":false,"q4Actions":[{"clock":"PT12M00.00S","scoreHome":71,"scoreAway":102},{"clock":"PT11M28.00S","scoreHome":73,"scoreAway":102},{"clock":"PT11M16.00S","scoreHome":73,"scoreAway":103},{"clock":"PT11M16.00S","scoreHome":73,"scoreAway":104},{"clock":"PT10M55.00S","scoreHome":73,"scoreAway":106},{"clock":"PT10M55.00S","scoreHome":73,"scoreAway":107},{"clock":"PT10M32.00S","scoreHome":73,"scoreAway":109},{"clock":"PT09M59.00S","scoreHome":75,"scoreAway":109},{"clock":"PT09M22.00S","scoreHome":78,"scoreAway":109},{"clock":"PT09M05.00S","scoreHome":78,"scoreAway":111},{"clock":"PT08M49.00S","scoreHome":81,"scoreAway":111},{"clock":"PT08M32.00S","scoreHome":81,"scoreAway":113},{"clock":"PT08M20.00S","scoreHome":84,"scoreAway":113},{"clock":"PT08M03.00S","scoreHome":84,"scoreAway":114},{"clock":"PT07M53.00S","scoreHome":86,"scoreAway":114},{"clock":"PT07M39.00S","scoreHome":86,"scoreAway":115},{"clock":"PT07M39.00S","scoreHome":86,"scoreAway":116},{"clock":"PT07M22.00S","scoreHome":88,"scoreAway":116},{"clock":"PT07M11.00S","scoreHome":88,"scoreAway":117},{"clock":"PT07M11.00S","scoreHome":88,"scoreAway":118},{"clock":"PT06M56.00S","scoreHome":90,"scoreAway":118},{"clock":"PT06M24.00S","scoreHome":93,"scoreAway":118},{"clock":"PT05M26.00S","scoreHome":93,"scoreAway":120},{"clock":"PT04M36.00S","scoreHome":93,"scoreAway":121},{"clock":"PT04M24.00S","scoreHome":96,"scoreAway":121},{"clock":"PT03M50.00S","scoreHome":98,"scoreAway":121},{"clock":"PT03M14.00S","scoreHome":98,"scoreAway":123},{"clock":"PT02M45.00S","scoreHome":101,"scoreAway":123},{"clock":"PT02M14.00S","scoreHome":103,"scoreAway":123},{"clock":"PT01M55.00S","scoreHome":103,"scoreAway":124},{"clock":"PT01M39.00S","scoreHome":105,"scoreAway":124},{"clock":"PT01M08.00S","scoreHome":106,"scoreAway":124},{"clock":"PT01M08.00S","scoreHome":107,"scoreAway":124},{"clock":"PT00M45.10S","scoreHome":109,"scoreAway":124},{"clock":"PT00M29.30S","scoreHome":109,"scoreAway":125},{"clock":"PT00M29.30S","scoreHome":109,"scoreAway":126},{"clock":"PT00M18.70S","scoreHome":111,"scoreAway":126},{"clock":"PT00M00.00S","scoreHome":111,"scoreAway":126}]}